a_john_shots/__init__.py
a_john_shots/core.py
a_john_shots/defaults.py
a_john_shots/hash.py
a_john_shots/helpers.py
a_john_shots-2.0.0.dist-info/LICENSE
a_john_shots-2.0.0.dist-info/METADATA
a_john_shots-2.0.0.dist-info/WHEEL
a_john_shots-2.0.0.dist-info/entry_points.txt
a_john_shots-2.0.0.dist-info/top_level.txt
a_john_shots-2.0.0.dist-info/RECORD
