Metadata-Version: 2.1
Name: a-john-shots
Version: 2.0.0
Summary: A tool to get the Security Hash Algorightms (SHA) of all file in a given path.
Home-page: https://github.com/funilrys/A-John-Shots
Author: funilrys
Author-email: contact@funilrys.com
License: MIT https://raw.githubusercontent.com/funilrys/A-John-Shots/master/LICENSE
Keywords: Python,JSON,SHA-1,SHA-512,SHA-224,SHA-384,SHA,MD5
Platform: any
Classifier: Environment :: Console
Classifier: Topic :: Software Development
Classifier: Development Status :: 5 - Production/Stable
Classifier: Intended Audience :: Developers
Classifier: Programming Language :: Python
Classifier: Programming Language :: Python :: 3
Classifier: License :: OSI Approved :: MIT License
